pyblast/__init__.py
pyblast/_version.py
pyblast/detector/__init__.py
pyblast/detector/mymodule.py
nublast-0.0.3.dist-info/LICENSE
nublast-0.0.3.dist-info/METADATA
nublast-0.0.3.dist-info/WHEEL
nublast-0.0.3.dist-info/top_level.txt
nublast-0.0.3.dist-info/RECORD
